chemlogic-0.1.1.dist-info/METADATA
chemlogic-0.1.1.dist-info/WHEEL
chemlogic-0.1.1.dist-info/entry_points.txt
chemlogic-0.1.1.dist-info/licenses/LICENSE
chemlogic/__init__.py
chemlogic/data/datasets/anti_sarscov2_activity/examples.txt
chemlogic/data/datasets/anti_sarscov2_activity/queries.txt
chemlogic/data/datasets/blood_brain_barrier/examples.txt
chemlogic/data/datasets/blood_brain_barrier/queries.txt
chemlogic/data/datasets/carcinogenous/examples.txt
chemlogic/data/datasets/carcinogenous/queries.txt
chemlogic/data/datasets/cox/examples.txt
chemlogic/data/datasets/cox/queries.txt
chemlogic/data/datasets/cyp2c9_substrate/examples.txt
chemlogic/data/datasets/cyp2c9_substrate/queries.txt
chemlogic/data/datasets/cyp2d6_substrate/examples.txt
chemlogic/data/datasets/cyp2d6_substrate/queries.txt
chemlogic/data/datasets/cyp3a4_substrate/examples.txt
chemlogic/data/datasets/cyp3a4_substrate/queries.txt
chemlogic/data/datasets/dhfr/examples.txt
chemlogic/data/datasets/dhfr/queries.txt
chemlogic/data/datasets/er/examples.txt
chemlogic/data/datasets/er/queries.txt
chemlogic/data/datasets/human_intestinal_absorption/examples.txt
chemlogic/data/datasets/human_intestinal_absorption/queries.txt
chemlogic/data/datasets/oral_bioavailability/examples.txt
chemlogic/data/datasets/oral_bioavailability/queries.txt
chemlogic/data/datasets/p_glycoprotein_inhibition/examples.txt
chemlogic/data/datasets/p_glycoprotein_inhibition/queries.txt
chemlogic/data/datasets/pampa_permeability/examples.txt
chemlogic/data/datasets/pampa_permeability/queries.txt
chemlogic/data/datasets/ptc/examples.txt
chemlogic/data/datasets/ptc/queries.txt
chemlogic/data/datasets/ptc_fm/examples.txt
chemlogic/data/datasets/ptc_fm/queries.txt
chemlogic/data/datasets/ptc_fr/examples.txt
chemlogic/data/datasets/ptc_fr/queries.txt
chemlogic/data/datasets/ptc_mm/examples.txt
chemlogic/data/datasets/ptc_mm/queries.txt
chemlogic/data/datasets/skin_reaction/examples.txt
chemlogic/data/datasets/skin_reaction/queries.txt
chemlogic/datasets/COX.py
chemlogic/datasets/CustomDataset.py
chemlogic/datasets/DHFR.py
chemlogic/datasets/Dataset.py
chemlogic/datasets/ER.py
chemlogic-0.1.1.dist-info/RECORD
