Metadata-Version: 2.1
Name: ChemLogic
Version: 0.1.1
Summary: ChemLogic is a neurosymbolic framework that integrates relational logic syntax with various graph neural network (GNN) architectures to model chemical knowledge. It encodes functional groups and molecular subgraph patterns into a differentiable, explainable architecture, enabling the construction of interpretable and modular GNN-based models for chemical reasoning.
Keywords: chemistry,differentiable,knowledge base,graph neural network,GNN,neurosymbolic,explainable,molecule,property,molecular property prediction,functional group,logic,logic programming,relational,relational logic,cheminformatics
Author-Email: =?utf-8?b?S2FpIEhvZMW+acSH?= <hodzic.e.k@outlook.com>
License: MIT License
Classifier: Development Status :: 3 - Alpha
Classifier: Intended Audience :: Science/Research
Classifier: Intended Audience :: Developers
Classifier: License :: OSI Approved :: MIT License
Classifier: Programming Language :: Python :: 3.11
Classifier: Topic :: Scientific/Engineering :: Artificial Intelligence
Classifier: Topic :: Scientific/Engineering :: Chemistry
Classifier: Topic :: Scientific/Engineering :: Information Analysis
Classifier: Operating System :: OS Independent
Project-URL: Homepage, https://github.com/erhc/ChemLogic
Requires-Python: >=3.11
Requires-Dist: neuralogic==0.7.16
Requires-Dist: optuna>=4.3.0
Requires-Dist: scikit-learn>=1.6.1
Requires-Dist: RDKit>=2025.3.2
Requires-Dist: pysmiles>=2.0.0
Requires-Dist: torch-geometric>=2.6.1
Requires-Dist: mlflow>=2.14.0
